src/yoklama/__init__.py
src/yoklama/ders.py
src/yoklama/ogrenciler.py
src/yoklama/yariyil.py
src/yoklama/yoklama.py
yoklama-2025.2.0.dist-info/METADATA
yoklama-2025.2.0.dist-info/WHEEL
yoklama-2025.2.0.dist-info/RECORD
